{
	"publications": [
		{
			"id": 1,
			"title": "Decadence Hair & Beauty",
			"pictures": [
				"https://source.unsplash.com/random/?barber",
				"https://source.unsplash.com/random/?hair",
				"https://source.unsplash.com/random/?spa",
				"https://source.unsplash.com/random/?makeup"
			],
			"location": "Tucuman",
			"description": "Sed sagittis. Nam congue, risus semper porta volutpat, quam pede lobortis ligula, sit amet eleifend pede libero quis orci. Nullam molestie nibh in lectus.\n\nPellentesque at nulla. Suspendisse potenti. Cras in purus eu magna vulputate luctus.",
			"date": "8/6/2008",
			"author": "Edsel Whimp",
			"category": "finance",
			"rating": 3.45,
			"reviews_count": 55,
			"attention_schedule": [
				{
					"day": "monday",
					"hours": "9:00 - 18:00"
				},
				{
					"day": "tuesday",
					"hours": "9:00 - 18:00"
				},
				{
					"day": "wednesday",
					"hours": "0:30 - 4:00"
				},
				{
					"day": "thursday",
					"hours": "9:00 - 18:00"
				},
				{
					"day": "friday",
					"hours": "9:00 - 18:00"
				},
				{
					"day": "saturday",
					"hours": "10:00 - 16:00"
				},
				{
					"day": "sunday",
					"hours": "Closed"
				}
			]
		}
	],
	"comments": [
		{
			"id": 1,
			"body": "some comment",
			"postId": 1
		}
	],
	"profile": {
		"name": "typicode"
	}
}
